datacloud/__about__.py
datacloud/__init__.py
datacloud-0.0.1.dist-info/METADATA
datacloud-0.0.1.dist-info/WHEEL
datacloud-0.0.1.dist-info/licenses/LICENSE.txt
datacloud-0.0.1.dist-info/RECORD
